vault_sync/__init__.py
vault_sync/cli.py
vault_sync/config.py
vault_sync/constants.py
vault_sync/exceptions.py
vault_sync/vault_sync.py
vault_sync-0.3.3.dist-info/METADATA
vault_sync-0.3.3.dist-info/WHEEL
vault_sync-0.3.3.dist-info/entry_points.txt
vault_sync-0.3.3.dist-info/RECORD
