Metadata-Version: 2.3
Name: vault-sync
Version: 0.3.3
Summary: Synchronization for Hashicorp vault key-value stores
License: MIT
Author: Vincent van Beek
Author-email: softwaredevelopment@solvinity.com
Requires-Python: >=3.9,<3.13
Classifier: License :: OSI Approved :: MIT License
Classifier: Programming Language :: Python :: 3
Classifier: Programming Language :: Python :: 3.9
Classifier: Programming Language :: Python :: 3.10
Classifier: Programming Language :: Python :: 3.11
Classifier: Programming Language :: Python :: 3.12
Requires-Dist: click (>=8.1.8,<9.0.0)
Requires-Dist: hvac (>=2.3.0,<3.0.0)
Requires-Dist: loguru (>=0.7.3,<0.8.0)
Requires-Dist: pydantic (<2.0)
Requires-Dist: schedule (>=1.2.2,<2.0.0)
